atomai/__init__.py
atomai/__version__.py
atomai/losses_metrics/__init__.py
atomai/losses_metrics/losses.py
atomai/losses_metrics/metrics.py
atomai/losses_metrics/vi_losses.py
atomai/models/__init__.py
atomai/models/classifier.py
atomai/models/denoiser.py
atomai/models/imspec.py
atomai/models/loaders.py
atomai/models/regressor.py
atomai/models/sam.py
atomai/models/segmentor.py
atomai/models/dgm/__init__.py
atomai/models/dgm/jrvae.py
atomai/models/dgm/jvae.py
atomai/models/dgm/rvae.py
atomai/models/dgm/vae.py
atomai/models/dklgp/__init__.py
atomai/models/dklgp/dklgpr.py
atomai/models/dklgp/gpr.py
atomai/nets/__init__.py
atomai/nets/blocks.py
atomai/nets/ed.py
atomai/nets/fcnn.py
atomai/nets/gp.py
atomai/nets/reg_cls.py
atomai/predictors/__init__.py
atomai/predictors/epredictor.py
atomai/predictors/predictor.py
atomai/stat/__init__.py
atomai/stat/fft_nmf.py
atomai/stat/multivar.py
atomai/stat/unmixer.py
atomai/trainers/__init__.py
atomai/trainers/etrainer.py
atomai/trainers/gptrainer.py
atomai/trainers/trainer.py
atomai/trainers/vitrainer.py
atomai/transforms/__init__.py
atomai/transforms/imaug.py
atomai/utils/__init__.py
atomai/utils/aseutils.py
atomai/utils/coords.py
atomai/utils/datasets.py
atomai/utils/graphx.py
atomai/utils/img.py
atomai/utils/imgen.py
atomai/utils/nn.py
atomai/utils/preproc.py
atomai/utils/viz.py
atomai-0.8.1.dist-info/licenses/LICENSE
test/__init__.py
test/models/__init__.py
test/models/test_dklgpr.py
test/models/test_gpr.py
test/models/test_loaders.py
test/models/test_vae.py
test/nets/__init__.py
test/nets/test_blocks.py
test/nets/test_gp.py
test/nets/test_reg_cls.py
test/predictors/__init__.py
test/predictors/test_epredictor.py
test/predictors/test_locator.py
test/predictors/test_predictor.py
test/stat/__init__.py
test/stat/test_multivar.py
test/trainers/__init__.py
test/trainers/test_etrainer.py
test/trainers/test_gptrainer.py
test/trainers/test_trainer.py
test/trainers/test_vitrainer.py
test/transforms/__init__.py
test/transforms/test_imaug.py
test/utils/__init__.py
atomai-0.8.1.dist-info/METADATA
atomai-0.8.1.dist-info/WHEEL
atomai-0.8.1.dist-info/top_level.txt
atomai-0.8.1.dist-info/RECORD
