Metadata-Version: 2.4
Name: atomai
Version: 0.8.1
Summary: Deep and machine learning for atom-resolved data
Home-page: https://github.com/pycroscopy/atomai/
Author: Maxim Ziatdinov
Author-email: maxim.ziatdinov@ai4microcopy.com
License: MIT license
Classifier: Programming Language :: Python
Classifier: Development Status :: 3 - Alpha
Classifier: Intended Audience :: Science/Research
Classifier: Operating System :: OS Independent
Classifier: Topic :: Scientific/Engineering
Requires-Python: >=3.8
License-File: LICENSE
Requires-Dist: torch>=1.0.0
Requires-Dist: numpy>=1.18.5
Requires-Dist: matplotlib>=3.4
Requires-Dist: scipy>=1.3.0
Requires-Dist: scikit-learn>=0.22.1
Requires-Dist: scikit-image>=0.16.2
Requires-Dist: opencv-python>=4.1.0
Requires-Dist: networkx>=2.5
Requires-Dist: mendeleev<=0.6.1
Requires-Dist: torchvision>=0.13.0
Requires-Dist: progressbar2>=3.38.0
Requires-Dist: gpytorch>=1.9.1
Requires-Dist: pandas>=1.1.5
Dynamic: author
Dynamic: author-email
Dynamic: classifier
Dynamic: description
Dynamic: description-content-type
Dynamic: home-page
Dynamic: license
Dynamic: license-file
Dynamic: requires-dist
Dynamic: requires-python
Dynamic: summary
